.gitignore
MANIFEST.in
README.rst
bootstrap.py
buildout.cfg
setup.cfg
setup.py
test-plone-4.0.x.cfg
test-plone-4.x.cfg
collective/__init__.py
collective.singing.egg-info/PKG-INFO
collective.singing.egg-info/SOURCES.txt
collective.singing.egg-info/dependency_links.txt
collective.singing.egg-info/entry_points.txt
collective.singing.egg-info/namespace_packages.txt
collective.singing.egg-info/not-zip-safe
collective.singing.egg-info/requires.txt
collective.singing.egg-info/top_level.txt
collective/singing/README.txt
collective/singing/__init__.py
collective/singing/async.py
collective/singing/async.txt
collective/singing/channel.py
collective/singing/collector.py
collective/singing/collector.txt
collective/singing/configure.zcml
collective/singing/interfaces.py
collective/singing/mail.py
collective/singing/message.py
collective/singing/message.txt
collective/singing/queue.py
collective/singing/queue.txt
collective/singing/rebuild_i18n.sh
collective/singing/scheduler.py
collective/singing/scheduler.txt
collective/singing/subscribe.py
collective/singing/subscribe.txt
collective/singing/tests.py
collective/singing/vocabularies.py
collective/singing/browser/__init__.py
collective/singing/browser/checkbox_hidden.pt
collective/singing/browser/collector.py
collective/singing/browser/configure.zcml
collective/singing/browser/converters.py
collective/singing/browser/converters.txt
collective/singing/browser/datamanager.py
collective/singing/browser/form.pt
collective/singing/browser/sub-edit.pt
collective/singing/browser/subscribe.py
collective/singing/browser/subscribe.txt
collective/singing/browser/tests.py
collective/singing/browser/utils.py
collective/singing/browser/widgets.zcml
collective/singing/browser/wizard-step.pt
collective/singing/browser/wizard.pt
collective/singing/browser/wizard.py
collective/singing/browser/wizard.txt
collective/singing/locales/collective.singing-manual.pot
collective/singing/locales/collective.singing.pot
collective/singing/locales/bg/LC_MESSAGES/collective.singing.mo
collective/singing/locales/bg/LC_MESSAGES/collective.singing.po
collective/singing/locales/ca/LC_MESSAGES/collective.singing.mo
collective/singing/locales/ca/LC_MESSAGES/collective.singing.po
collective/singing/locales/cs/LC_MESSAGES/collective.singing.mo
collective/singing/locales/cs/LC_MESSAGES/collective.singing.po
