Metadata-Version: 1.1
Name: collective.singing
Version: 0.7.5
Summary: A Zope 3 library for sending notifications and newsletters
Home-page: http://pypi.python.org/pypi/collective.singing
Author: Daniel Nouri, Thomas Clement Mogensen and contributors
Author-email: singing-dancing@googlegroups.com
License: GPL
Keywords: zope plone notification newsletter
Platform: UNKNOWN
Classifier: Framework :: Plone
Classifier: Framework :: Plone :: 3.2
Classifier: Framework :: Plone :: 3.3
Classifier: Framework :: Plone :: 4.0
Classifier: Framework :: Plone :: 4.1
Classifier: Framework :: Zope2
Classifier: Framework :: Zope3
Classifier: Programming Language :: Python
Classifier: Topic :: Software Development :: Libraries :: Python Modules
